LICENSE
README.md
setup.py
calculator/__init__.py
calculator/calculator_rhsm.py
calculator_rhsm.egg-info/PKG-INFO
calculator_rhsm.egg-info/SOURCES.txt
calculator_rhsm.egg-info/dependency_links.txt
calculator_rhsm.egg-info/top_level.txt